Metadata-Version: 2.1
Name: tikload
Version: 1.0
Summary: download tiktok video
Author-email: jomeyjq@gmail.com
